{
  "kind": "collectionType",
  "collectionName": "pages",
  "info": {
    "singularName": "page",
    "pluralName": "pages",
    "displayName": "page",
    "description": ""
  },
  "options": {
    "draftAndPublish": true
  },
  "pluginOptions": {},
  "attributes": {
    "namePage": {
      "type": "string"
    },
    "slug": {
      "type": "uid",
      "targetField": "namePage"
    },
    "promo": {
      "type": "component",
      "component": "promo.promo",
      "repeatable": true
    },
    "plan": {
      "type": "component",
      "component": "pricing.plan",
      "repeatable": true
    },
    "hero": {
      "type": "component",
      "component": "hero.hero",
      "repeatable": false
    },
    "values": {
      "type": "component",
      "component": "feature.features",
      "repeatable": true
    },
    "features": {
      "type": "component",
      "component": "feature.features",
      "repeatable": true
    },
    "steps": {
      "type": "component",
      "component": "feature.features",
      "repeatable": true
    },
    "stats": {
      "type": "component",
      "component": "service.services",
      "repeatable": true
    },
    "Contact": {
      "type": "component",
      "component": "contact.contact",
      "repeatable": false
    },
    "imagenRe1": {
      "type": "media",
      "multiple": false,
      "required": false,
      "allowedTypes": [
        "images",
        "files",
        "videos",
        "audios"
      ]
    },
    "landingPageJson": {
      "type": "json"
    },
    "gallery": {
      "type": "component",
      "component": "gallery.gallery",
      "repeatable": false
    },
    "videos": {
      "type": "component",
      "component": "video-id.youtube-video",
      "repeatable": true
    },
    "badge": {
      "type": "component",
      "component": "badge.badge",
      "repeatable": true
    }
  }
}
